setup.py
quick/__init__.py
quick/arbitrary.py
quick/basic_types.py
quick/core.py
quick/features.py
quick/generators.py
quick/shrink.py
quick.py.egg-info/PKG-INFO
quick.py.egg-info/SOURCES.txt
quick.py.egg-info/dependency_links.txt
quick.py.egg-info/top_level.txt