Metadata-Version: 1.1
Name: quick.py
Version: 1.0.0
Summary: quick.py is property-based testing library for Python inspired by the Haskell library QuickCheck
Home-page: https://github.com/msoedov/quick.py
Author: Alex Myasoedov
Author-email: msoedov@gmail.com
License: MIT
Keywords: testing library
Platform: UNKNOWN
Classifier: Development Status :: 2 - Pre-Alpha
Classifier: Intended Audience :: Developers
Classifier: Operating System :: OS Independent
Classifier: Topic :: Software Development :: Libraries
Classifier: License :: OSI Approved :: MIT License
Classifier: Intended Audience :: Developers
Classifier: Programming Language :: Python :: 3
Classifier: Programming Language :: Python :: 3 :: Only
Classifier: Programming Language :: Python :: 3.2
Classifier: Programming Language :: Python :: 3.3
Classifier: Programming Language :: Python :: 3.4
Classifier: Programming Language :: Python :: 3.5
